CHANGES.txt
base.cfg
bootstrap.py
setup.py
src/five/__init__.py
src/five.hashedresource.egg-info/PKG-INFO
src/five.hashedresource.egg-info/SOURCES.txt
src/five.hashedresource.egg-info/dependency_links.txt
src/five.hashedresource.egg-info/namespace_packages.txt
src/five.hashedresource.egg-info/not-zip-safe
src/five.hashedresource.egg-info/requires.txt
src/five.hashedresource.egg-info/top_level.txt
src/five/hashedresource/README.txt
src/five/hashedresource/__debug_mode__.py
src/five/hashedresource/__init__.py
src/five/hashedresource/configure.zcml
src/five/hashedresource/ftesting-devmode.zcml
src/five/hashedresource/ftesting.zcml
src/five/hashedresource/testing.py
src/five/hashedresource/url.py
src/five/hashedresource/tests/__init__.py
src/five/hashedresource/tests/test_browser.py
src/five/hashedresource/tests/test_hash.py
src/five/hashedresource/tests/test_url.py