Metadata-Version: 1.0
Name: five.hashedresource
Version: 1.1
Summary: Provides URLs for resources that change whenever their content changes.
Home-page: http://pypi.python.org/pypi/five.hashedresource
Author: gocept gmbh & co. kg
Author-email: sw@gocept.com
License: ZPL 2.1
Platform: UNKNOWN
Classifier: Intended Audience :: Developers
Classifier: License :: OSI Approved :: Zope Public License
Classifier: Programming Language :: Python
Classifier: Operating System :: OS Independent
Classifier: Framework :: Zope2
